GPTDriver/ChatGPT.py
GPTDriver/__init__.py
GPTDriver-0.1.1.dist-info/LICENSE
GPTDriver-0.1.1.dist-info/METADATA
GPTDriver-0.1.1.dist-info/WHEEL
GPTDriver-0.1.1.dist-info/top_level.txt
GPTDriver-0.1.1.dist-info/RECORD
