Metadata-Version: 2.1
Name: GPTDriver
Version: 0.1.1
Summary: Selenium Driver to Control ChatGPT from Command Lines
Home-page: https://github.com/nilbasora/GPTDriver
Author: Nil Basora
Author-email: nilbasora@gmail.com
License: MIT
Keywords: GPT,OpenAI,ChatGPT,Selenium,Driver
Platform: UNKNOWN
Classifier: Development Status :: 3 - Alpha
Classifier: Intended Audience :: Developers
Classifier: Topic :: Software Development :: Build Tools
Classifier: License :: OSI Approved :: MIT License
Classifier: Programming Language :: Python :: 3.6
Classifier: Programming Language :: Python :: 3.7
Classifier: Programming Language :: Python :: 3.8
Classifier: Programming Language :: Python :: 3.9
Classifier: Programming Language :: Python :: 3.10
Classifier: Programming Language :: Python :: 3.11
License-File: LICENSE
Requires-Dist: selenium (==4.10.0)
Requires-Dist: undetected-chromedriver (==3.5.0)
